anonypy/__init__.py
anonypy/anonymity.py
anonypy/anonypy.py
anonypy/attack.py
anonypy/mondrian.py
anonypy/util.py
anonypy-0.2.1.dist-info/METADATA
anonypy-0.2.1.dist-info/WHEEL
anonypy-0.2.1.dist-info/licenses/LICENSE
anonypy-0.2.1.dist-info/RECORD
