Metadata-Version: 2.3
Name: anonypy
Version: 0.2.1
Summary: Anonymization library for python
Project-URL: Homepage, https://github.com/glassonion1/anonypy
Project-URL: Bug Tracker, https://github.com/glassonion1/anonypy/issues
Author-email: glassonion1 <glassonion999@gmail.com>
License-File: LICENSE
Keywords: k-anonymity,l-diversity,mondrian,t-closeness
Requires-Python: >=3.10
